kingbirdclient/__init__.py
kingbirdclient/exceptions.py
kingbirdclient/shell.py
kingbirdclient/utils.py
kingbirdclient/api/__init__.py
kingbirdclient/api/base.py
kingbirdclient/api/client.py
kingbirdclient/api/httpclient.py
kingbirdclient/api/v1/__init__.py
kingbirdclient/api/v1/client.py
kingbirdclient/api/v1/quota_class_manager.py
kingbirdclient/api/v1/quota_manager.py
kingbirdclient/api/v1/sync_manager.py
kingbirdclient/commands/README.rst
kingbirdclient/commands/__init__.py
kingbirdclient/commands/v1/__init__.py
kingbirdclient/commands/v1/base.py
kingbirdclient/commands/v1/quota_class_manager.py
kingbirdclient/commands/v1/quota_manager.py
kingbirdclient/commands/v1/sync_manager.py
kingbirdclient/openstack/__init__.py
kingbirdclient/openstack/common/__init__.py
kingbirdclient/openstack/common/cliutils.py
kingbirdclient/openstack/common/gettextutils.py
kingbirdclient/openstack/common/importutils.py
kingbirdclient/openstack/common/strutils.py
kingbirdclient/openstack/common/uuidutils.py
kingbirdclient/openstack/common/apiclient/__init__.py
kingbirdclient/openstack/common/apiclient/auth.py
kingbirdclient/openstack/common/apiclient/base.py
kingbirdclient/openstack/common/apiclient/client.py
kingbirdclient/openstack/common/apiclient/exceptions.py
kingbirdclient/openstack/common/apiclient/fake_client.py
kingbirdclient/osc/__init__.py
kingbirdclient/osc/plugin.py
kingbirdclient/tests/__init__.py
kingbirdclient/tests/base.py
kingbirdclient/tests/base_shell_test.py
kingbirdclient/tests/test_client.py
kingbirdclient/tests/test_help_and_bash_completion.py
kingbirdclient/tests/test_httpclient.py
kingbirdclient/tests/test_shell.py
kingbirdclient/tests/test_utils.py
kingbirdclient/tests/v1/__init__.py
kingbirdclient/tests/v1/test_quota_class_manager.py
kingbirdclient/tests/v1/test_quota_manager.py
kingbirdclient/tests/v1/test_sync_manager.py
python_kingbirdclient-0.2.1.dist-info/DESCRIPTION.rst
python_kingbirdclient-0.2.1.dist-info/METADATA
python_kingbirdclient-0.2.1.dist-info/RECORD
python_kingbirdclient-0.2.1.dist-info/WHEEL
python_kingbirdclient-0.2.1.dist-info/entry_points.txt
python_kingbirdclient-0.2.1.dist-info/metadata.json
python_kingbirdclient-0.2.1.dist-info/pbr.json
python_kingbirdclient-0.2.1.dist-info/top_level.txt
